Testomatio.py
api_connectors/__init__.py
api_connectors/testomatio_connector.py
models/__init__.py
models/test_item.py
models/testomat_item.py
models/testrun_config.py
reporter/__init__.py
reporter/listener.py
utils/__init__.py
utils/constants.py
utils/test_parser.py
utils/utils.py
robot_framework_reporter-0.2.1.dist-info/METADATA
robot_framework_reporter-0.2.1.dist-info/WHEEL
robot_framework_reporter-0.2.1.dist-info/entry_points.txt
robot_framework_reporter-0.2.1.dist-info/top_level.txt
robot_framework_reporter-0.2.1.dist-info/RECORD
