Metadata-Version: 2.4
Name: robot-framework-reporter
Version: 0.2.1
Summary: Robot Framework plugin for sync and report test to testomat.io
Author-email: Vladyslav Krutko <krutkovladyslav@gmail.com>
License: MIT
Project-URL: Testomat.io, https://testomat.io/
Project-URL: Homepage, https://github.com/testomatio/robot-framework-reporter
Project-URL: Bug Tracker, https://github.com/testomatio/robot-framework-reporter/issues
Keywords: robotframework,testing,reporter,plugin
Classifier: Framework :: Robot Framework
Classifier: Framework :: Robot Framework :: Library
Classifier: Programming Language :: Python :: 3
Classifier: License :: OSI Approved :: MIT License
Classifier: Operating System :: OS Independent
Requires-Python: >=3.10
Requires-Dist: robotframework>=4.0
Requires-Dist: requests>=2.25.0
Provides-Extra: dev
Requires-Dist: pytest>=7.0; extra == "dev"
